{
  "transactions": [
    {
      "id": 1,
      "description": "Desenvolvimento de site",
      "type": "income",
      "category": "Venda",
      "price": 14000,
      "createdAt": "2022-12-12T20:05:01.093Z"
    },
    {
      "id": 2,
      "description": "Hambúrguer",
      "type": "outcome",
      "category": "Alimentação",
      "price": 50,
      "createdAt": "2022-12-12T10:05:01.093Z"
    },
    {
      "id": 3,
      "description": "Ignite Rocketseat",
      "type": "outcome",
      "category": "Educação",
      "price": 1980,
      "createdAt": "2022-12-12T05:05:01.093Z"
    },
    {
      "description": "Desenvolvimento de app",
      "price": 10000,
      "category": "Venda",
      "type": "income",
      "createdAt": "2022-12-13T13:16:09.622Z",
      "id": 4
    },
    {
      "description": "Pastel",
      "price": 5,
      "category": "Alimentação",
      "type": "outcome",
      "createdAt": "2022-12-13T13:22:37.948Z",
      "id": 5
    },
    {
      "description": "Iogurte de Banana",
      "price": 4,
      "category": "Alimentação",
      "type": "outcome",
      "createdAt": "2022-12-13T13:33:33.987Z",
      "id": 6
    }
  ]
}